AJWorkFlow/__init__.py
AJWorkFlow/Display/Graphs2D.py
AJWorkFlow/Display/__init__.py
AJWorkFlow/Display/tables.py
AJWorkFlow/Process/__init__.py
AJWorkFlow/Process/loops.py
AJWorkFlow-1.0.1.data/scripts/AJWorkFlow
AJWorkFlow_pkg/__init__.py
AJWorkFlow_pkg/Display/Graphs2D.py
AJWorkFlow_pkg/Display/__init__.py
AJWorkFlow_pkg/Display/tables.py
AJWorkFlow_pkg/Process/__init__.py
AJWorkFlow_pkg/Process/loops.py
AJWorkFlow-1.0.1.dist-info/METADATA
AJWorkFlow-1.0.1.dist-info/WHEEL
AJWorkFlow-1.0.1.dist-info/top_level.txt
AJWorkFlow-1.0.1.dist-info/RECORD
