Metadata-Version: 2.1
Name: AJWorkFlow
Version: 1.0.1
Summary: Package to display data and realize multiple operations with ease
Home-page: https://github.com/DemiurgeApeiron/AJWorkFlow
Author: DemiurgeApeiron
Author-email: alexmar.noe@gmail.com
License: UNKNOWN
Platform: UNKNOWN
Classifier: Programming Language :: Python :: 3.8
Classifier: License :: OSI Approved :: MIT License
Classifier: Operating System :: OS Independent
